{"run_number": "1736073007363612", "step_name": "start", "task_id": "1", "attempt_id": 0, "name": "_exception", "content_type": "gzip+pickle-v2", "type": "metaflow.artifact", "sha": "08d75c0a3d4f06357648fb9a439b538e6e6874be", "ds_type": "local", "location": ":root:/Users/dimasrizki/Documents/ipsd/L196_Tugas Sebelum UAS/.metaflow", "flow_id": "ClusteringFlow", "user_name": "dimasrizki", "tags": [], "system_tags": ["metaflow_version:2.13", "runtime:dev", "user:dimasrizki", "python_version:3.12.4"], "ts_epoch": 1736073008134}